rnnsim/RNN.py
rnnsim/__init__.py
rnnsim/__main__.py
rnnsim/model.py
rnnsim/utils.py
rnnsim-0.1.dist-info/entry_points.txt
rnnsim-0.1.dist-info/LICENSE.md
rnnsim-0.1.dist-info/WHEEL
rnnsim-0.1.dist-info/METADATA
rnnsim-0.1.dist-info/RECORD
