Metadata-Version: 2.1
Name: rnnsim
Version: 0.1
Summary: Random Neural Network Simulator implemented in Python.
Home-page: https://pypi.org/project/rnnsim
License: MIT
Author: Mandar Gogate
Author-email: contact@mandargogate.com
Requires-Python: >=3.6,<4.0
Classifier: Development Status :: 1 - Planning
Classifier: License :: OSI Approved :: MIT License
Classifier: Natural Language :: English
Classifier: Operating System :: OS Independent
Classifier: Programming Language :: Python
Classifier: Programming Language :: Python :: 3
Classifier: Programming Language :: Python :: 3.6
Classifier: Programming Language :: Python :: 3.7
Requires-Dist: numpy (>=1.16.1,<2.0.0)
Project-URL: Documentation, https://rnnsim.readthedocs.io
Project-URL: Repository, https://github.com/MandarGogate/RNNSim
